yt_metadata_verifier/__init__.py
yt_metadata_verifier/cli.py
yt_metadata_verifier-1.0.2.dist-info/entry_points.txt
yt_metadata_verifier-1.0.2.dist-info/LICENSE
yt_metadata_verifier-1.0.2.dist-info/METADATA
yt_metadata_verifier-1.0.2.dist-info/WHEEL
yt_metadata_verifier-1.0.2.dist-info/RECORD
