Metadata-Version: 2.1
Name: yt-metadata-verifier
Version: 1.0.2
Summary: CLI tool to fetch and verify YouTube video metadata
Home-page: https://github.com/taj54
License: MIT
Author: Taj
Author-email: tajulislamj200@gmail.com
Requires-Python: >=3.10,<3.12.5
Classifier: License :: OSI Approved :: MIT License
Classifier: Programming Language :: Python :: 3
Classifier: Programming Language :: Python :: 3.10
Classifier: Programming Language :: Python :: 3.11
Classifier: Programming Language :: Python :: 3.12
Requires-Dist: yt-dlp (>=2025.6.25,<2026.0.0)
Project-URL: Repository, https://github.com/taj54/youtube_metadata_verifier
